quoted/__init__.py
quoted/quoted.py
quoted/scrapy/__init__.py
quoted/scrapy/extensions/__init__.py
quoted/scrapy/extensions/storage.py
quoted/scrapy/spiders/__init__.py
quoted/scrapy/spiders/brainyquote.py
quoted/scrapy/spiders/goodreads.py
quoted/scrapy/spiders/toscrape.py
quoted-0.4.1.dist-info/entry_points.txt
quoted-0.4.1.dist-info/LICENSE
quoted-0.4.1.dist-info/WHEEL
quoted-0.4.1.dist-info/METADATA
quoted-0.4.1.dist-info/RECORD
