Metadata-Version: 2.1
Name: quoted
Version: 0.4.1
Summary: Feed your brain with the best random quotes from multiple web portals.
Home-page: https://github.com/rcares/quoted/
License: MIT
Keywords: Quote,Motivation,Words,Reflect,Meditate
Author: Rodrigo Cares
Author-email: rcares@gmail.com
Maintainer: Rodrigo Cares
Maintainer-email: rcares@gmail.com
Requires-Python: >=3.6,<4.0
Classifier: License :: OSI Approved :: MIT License
Classifier: Programming Language :: Python :: 3
Classifier: Programming Language :: Python :: 3.6
Classifier: Programming Language :: Python :: 3.7
Classifier: Programming Language :: Python :: 3.8
Requires-Dist: click (>=7.1.2,<8.0.0)
Requires-Dist: importlib-metadata (>=1.6.0,<2.0.0)
Requires-Dist: rich (>=1.0.3,<2.0.0)
Requires-Dist: scrapy (>=2.1.0,<3.0.0)
Project-URL: Documentation, https://github.com/rcares/quoted/
Project-URL: Repository, https://github.com/rcares/quoted/
Project-URL: issues, https://github.com/rcares/quoted/issues
Project-URL: source, https://github.com/rcares/quoted/
